{
  "metrics": {
    "abox_axiom_count": 0,
    "abox_axiom_count_incl": 0,
    "annotation_property_count": 13,
    "annotation_property_count_incl": 13,
    "axiom_count": 349945,
    "axiom_count_incl": 349945,
    "class_count": 31683,
    "class_count_incl": 31683,
    "dataproperty_count": 0,
    "dataproperty_count_incl": 0,
    "datatypes_count": 2,
    "datatypes_count_incl": 2,
    "dt_builtin_count": 2,
    "dt_builtin_count_incl": 2,
    "dt_notbuiltin_count": 0,
    "dt_notbuiltin_count_incl": 0,
    "expressivity": "E",
    "expressivity_incl": "E",
    "individual_count": 0,
    "individual_count_incl": 0,
    "logical_axiom_count": 36367,
    "logical_axiom_count_incl": 36367,
    "obj_property_count": 6,
    "obj_property_count_incl": 6,
    "ontology_anno_count": 1,
    "ontology_iri": "http://purl.obolibrary.org/obo/mondo/sources/omim.owl",
    "ontology_version_iri": "http://purl.obolibrary.org/obo/mondo/sources/2024-01-31/omim.owl",
    "owl2": true,
    "owl2_dl": true,
    "owl2_el": true,
    "owl2_ql": true,
    "owl2_rl": false,
    "rbox_axiom_count": 0,
    "rbox_axiom_count_incl": 0,
    "rdfs": false,
    "rule_count": 0,
    "rule_count_incl": 0,
    "signature_entity_count": 31704,
    "signature_entity_count_incl": 31704,
    "syntax": "RDF/XML Syntax",
    "tbox_axiom_count": 36367,
    "tbox_axiom_count_incl": 36367,
    "tboxrbox_axiom_count": 36367,
    "tboxrbox_axiom_count_incl": 36367,
    "axiom_types": [
      "AnnotationAssertion",
      "Declaration",
      "SubClassOf"
    ],
    "axiom_types_incl": [
      "AnnotationAssertion",
      "Declaration",
      "SubClassOf"
    ],
    "constructs": [
      "FULL_EXISTENTIAL"
    ],
    "constructs_incl": [
      "FULL_EXISTENTIAL"
    ],
    "valid_imports": [],
    "valid_imports_incl": [],
    "axiom_type_count": {
      "AnnotationAssertion": 281880,
      "Declaration": 31698,
      "SubClassOf": 36367
    },
    "axiom_type_count_incl": {
      "AnnotationAssertion": 281880,
      "Declaration": 31698,
      "SubClassOf": 36367
    },
    "class_expression_count": {
      "Class": 104411,
      "ObjectSomeValuesFrom": 14302
    },
    "class_expression_count_incl": {
      "Class": 104411,
      "ObjectSomeValuesFrom": 14302
    },
    "curie_map": {
      "oboInOwl": "http://www.geneontology.org/formats/oboInOwl#",
      "MONDO": "http://purl.obolibrary.org/obo/MONDO_",
      "rdf": "http://www.w3.org/1999/02/22-rdf-syntax-ns#",
      "owl": "http://www.w3.org/2002/07/owl#",
      "IAO": "http://purl.obolibrary.org/obo/IAO_",
      "xsd": "http://www.w3.org/2001/XMLSchema#",
      "skos": "http://www.w3.org/2004/02/skos/core#",
      "rdfs": "http://www.w3.org/2000/01/rdf-schema#",
      "biolink": "https://w3id.org/biolink/vocab/",
      "CHR": "http://purl.obolibrary.org/obo/CHR_",
      "SO": "http://purl.obolibrary.org/obo/SO_",
      "RO": "http://purl.obolibrary.org/obo/RO_"
    },
    "namespace_axiom_count": {
      "prefix_unknown": 79648,
      "oboInOwl": 91130,
      "MONDO": 18960,
      "rdf": 7142,
      "owl": 1359,
      "IAO": 55201,
      "skos": 59999,
      "rdfs": 36406,
      "biolink": 33218,
      "CHR": 7546,
      "SO": 17217,
      "RO": 14308
    },
    "namespace_axiom_count_incl": {
      "prefix_unknown": 79648,
      "oboInOwl": 91130,
      "MONDO": 18960,
      "rdf": 7142,
      "owl": 1359,
      "IAO": 55201,
      "skos": 59999,
      "rdfs": 36406,
      "biolink": 33218,
      "CHR": 7546,
      "SO": 17217,
      "RO": 14308
    },
    "namespace_entity_count": {
      "prefix_unknown": 30236,
      "oboInOwl": 3,
      "owl": 2,
      "xsd": 1,
      "skos": 1,
      "rdfs": 2,
      "CHR": 1446,
      "MONDO": 1,
      "rdf": 1,
      "IAO": 2,
      "SO": 1,
      "biolink": 2,
      "RO": 6
    },
    "namespace_entity_count_incl": {
      "prefix_unknown": 30236,
      "oboInOwl": 3,
      "owl": 2,
      "xsd": 1,
      "skos": 1,
      "rdfs": 2,
      "CHR": 1446,
      "MONDO": 1,
      "rdf": 1,
      "IAO": 2,
      "SO": 1,
      "biolink": 2,
      "RO": 6
    },
    "owl2dl_profile_violation": {}
  }
}